ip_validation/__init__.py
ip_validation/const.py
ip_validation/mets.py
ip_validation/rules.py
ip_validation/structure.py
ip_validation/cli/__init__.py
ip_validation/cli/app.py
ip_validation/infopacks/__init__.py
ip_validation/infopacks/information_package.py
ip_validation/infopacks/manifest.py
ip_validation/specifications/__init__.py
ip_validation/specifications/specification.py
ip_validation/specifications/struct_reqs.py
ip_validation/xml/__init__.py
ip_validation/xml/namespaces.py
ip_validation/xml/schema.py
ip_validation/xml/schematron.py
ip_validation/xml/resources/__init__.py
ip_validation/xml/resources/profiles/E-ARK-CSIP.xml
ip_validation/xml/resources/profiles/E-ARK-DIP.xml
ip_validation/xml/resources/profiles/E-ARK-SIP.xml
ip_validation/xml/resources/profiles/__init__.py
ip_validation/xml/resources/schema/DILCISExtensionMETS.xsd
ip_validation/xml/resources/schema/DILCISExtensionSIPMETS.xsd
ip_validation/xml/resources/schema/__init__.py
ip_validation/xml/resources/schema/mets.csip.local.v2-0.xsd
ip_validation/xml/resources/schema/mets.profile.local.v2-0.xsd
ip_validation/xml/resources/schema/mets.profile.v2-0.xsd
ip_validation/xml/resources/schema/mets.sip.local.v2-0.xsd
ip_validation/xml/resources/schema/mets.xsd
ip_validation/xml/resources/schema/xhtml1-strict.xsd
ip_validation/xml/resources/schema/xlink.xsd
ip_validation/xml/resources/schema/xml.xsd
ip_validation/xml/resources/schematron/__init__.py
tests/__init__.py
tests/archive_handler_test.py
tests/ips_test.py
tests/manifests_test.py
tests/mets_test.py
tests/namespaces_test.py
tests/rules_test.py
tests/schematron_test.py
tests/specification_test.py
tests/structure_test.py
tests/utils_test.py
py_eark_ip_validator-1.1.1.dist-info/METADATA
py_eark_ip_validator-1.1.1.dist-info/WHEEL
py_eark_ip_validator-1.1.1.dist-info/entry_points.txt
py_eark_ip_validator-1.1.1.dist-info/top_level.txt
py_eark_ip_validator-1.1.1.dist-info/RECORD
