Metadata-Version: 2.1
Name: py-eark-ip-validator
Version: 1.1.1
Summary: E-ARK Python Information Package Validation
Home-page: https://www.e-ark-foundation.eu/e-ark-software-py-e-ark-ip-validator/
Download-URL: https://github.com/E-ARK-Software/py-e-ark-ip-validator/archive/1.1.1.tar.gz
Author: E-ARK Foundation
Author-email: admin@e-ark-foundation.eu
Maintainer: E-ARK Foundation
Maintainer-email: admin@e-ark-foundation.eu
License: Apache License 2.0
Classifier: Intended Audience :: Developers
Classifier: Programming Language :: Python :: 3
Classifier: Programming Language :: Python :: 3.5
Classifier: Programming Language :: Python :: 3.6
Classifier: Topic :: System :: Archiving
Requires-Dist: setuptools
Requires-Dist: lxml
Requires-Dist: importlib-resources
Provides-Extra: setup
Requires-Dist: pytest-runner ; extra == 'setup'
Provides-Extra: testing
Requires-Dist: pre-commit ; extra == 'testing'
Requires-Dist: pytest ; extra == 'testing'
Requires-Dist: pylint ; extra == 'testing'
Requires-Dist: pytest-cov ; extra == 'testing'
